[{"season":2025,"week":1,"type":"REG","date":"2025-09-04","home":"PHI","away":"DAL","home_score":24,"away_score":20,"winner":"PHI"},{"season":2025,"week":1,"type":"REG","date":"2025-09-05","home":"LAC","away":"KC","home_score":27,"away_score":21,"winner":"LAC"},{"season":2025,"week":1,"type":"REG","date":"2025-09-07","home":"ATL","away":"TB","home_score":20,"away_score":23,"winner":"TB"},{"season":2025,"week":1,"type":"REG","date":"2025-09-07","home":"CLE","away":"CIN","home_score":16,"away_score":17,"winner":"CIN"},{"season":2025,"week":1,"type":"REG","date":"2025-09-07","home":"IND","away":"MIA","home_score":33,"away_score":8,"winner":"IND"},{"season":2025,"week":1,"type":"REG","date":"2025-09-07","home":"JAX","away":"CAR","home_score":26,"away_score":10,"winner":"JAX"},{"season":2025,"week":1,"type":"REG","date":"2025-09-07","home":"NE","away":"LV","home_score":13,"away_score":20,"winner":"LV"},{"season":2025,"week":1,"type":"REG","date":"2025-09-07","home":"NO","away":"ARI","home_score":13,"away_score":20,"winner":"ARI"},{"season":2025,"week":1,"type":"REG","date":"2025-09-07","home":"NYJ","away":"PIT","home_score":32,"away_score":34,"winner":"PIT"},{"season":2025,"week":1,"type":"REG","date":"2025-09-07","home":"WAS","away":"NYG","home_score":21,"away_score":6,"winner":"WAS"},{"season":2025,"week":1,"type":"REG","date":"2025-09-07","home":"DEN","away":"TEN","home_score":20,"away_score":12,"winner":"DEN"},{"season":2025,"week":1,"type":"REG","date":"2025-09-07","home":"SEA","away":"SF","home_score":13,"away_score":17,"winner":"SF"},{"season":2025,"week":1,"type":"REG","date":"2025-09-07","home":"GB","away":"DET","home_score":27,"away_score":13,"winner":"GB"},{"season":2025,"week":1,"type":"REG","date":"2025-09-07","home":"LA","away":"HOU","home_score":14,"away_score":9,"winner":"LA"},{"season":2025,"week":1,"type":"REG","date":"2025-09-07","home":"BUF","away":"BAL","home_score":41,"away_score":40,"winner":"BUF"},{"season":2025,"week":1,"type":"REG","date":"2025-09-08","home":"CHI","away":"MIN","home_score":24,"away_score":27,"winner":"MIN"},{"season":2025,"week":2,"type":"REG","date":"2025-09-11","home":"GB","away":"WAS","home_score":27,"away_score":18,"winner":"GB"},{"season":2025,"week":2,"type":"REG","date":"2025-09-14","home":"BAL","away":"CLE","home_score":41,"away_score":17,"winner":"BAL"},{"season":2025,"week":2,"type":"REG","date":"2025-09-14","home":"CIN","away":"JAX","home_score":31,"away_score":27,"winner":"CIN"},{"season":2025,"week":2,"type":"REG","date":"2025-09-14","home":"DAL","away":"NYG","home_score":40,"away_score":37,"winner":"DAL"},{"season":2025,"week":2,"type":"REG","date":"2025-09-14","home":"DET","away":"CHI","home_score":52,"away_score":21,"winner":"DET"},{"season":2025,"week":2,"type":"REG","date":"2025-09-14","home":"MIA","away":"NE","home_score":27,"away_score":33,"winner":"NE"},{"season":2025,"week":2,"type":"REG","date":"2025-09-14","home":"NO","away":"SF","home_score":21,"away_score":26,"winner":"SF"},{"season":2025,"week":2,"type":"REG","date":"2025-09-14","home":"NYJ","away":"BUF","home_score":10,"away_score":30,"winner":"BUF"},{"season":2025,"week":2,"type":"REG","date":"2025-09-14","home":"PIT","away":"SEA","home_score":17,"away_score":31,"winner":"SEA"},{"season":2025,"week":2,"type":"REG","date":"2025-09-14","home":"TEN","away":"LA","home_score":19,"away_score":33,"winner":"LA"},{"season":2025,"week":2,"type":"REG","date":"2025-09-14","home":"ARI","away":"CAR","home_score":27,"away_score":22,"winner":"ARI"},{"season":2025,"week":2,"type":"REG","date":"2025-09-14","home":"IND","away":"DEN","home_score":29,"away_score":28,"winner":"IND"},{"season":2025,"week":2,"type":"REG","date":"2025-09-14","home":"KC","away":"PHI","home_score":17,"away_score":20,"winner":"PHI"},{"season":2025,"week":2,"type":"REG","date":"2025-09-14","home":"MIN","away":"ATL","home_score":6,"away_score":22,"winner":"ATL"},{"season":2025,"week":2,"type":"REG","date":"2025-09-15","home":"HOU","away":"TB","home_score":19,"away_score":20,"winner":"TB"},{"season":2025,"week":2,"type":"REG","date":"2025-09-15","home":"LV","away":"LAC","home_score":9,"away_score":20,"winner":"LAC"},{"season":2025,"week":3,"type":"REG","date":"2025-09-18","home":"BUF","away":"MIA","home_score":31,"away_score":21,"winner":"BUF"},{"season":2025,"week":3,"type":"REG","date":"2025-09-21","home":"CAR","away":"ATL","home_score":30,"away_score":0,"winner":"CAR"},{"season":2025,"week":3,"type":"REG","date":"2025-09-21","home":"CLE","away":"GB","home_score":13,"away_score":10,"winner":"CLE"},{"season":2025,"week":3,"type":"REG","date":"2025-09-21","home":"JAX","away":"HOU","home_score":17,"away_score":10,"winner":"JAX"},{"season":2025,"week":3,"type":"REG","date":"2025-09-21","home":"MIN","away":"CIN","home_score":48,"away_score":10,"winner":"MIN"},{"season":2025,"week":3,"type":"REG","date":"2025-09-21","home":"NE","away":"PIT","home_score":14,"away_score":21,"winner":"PIT"},{"season":2025,"week":3,"type":"REG","date":"2025-09-21","home":"PHI","away":"LA","home_score":33,"away_score":26,"winner":"PHI"},{"season":2025,"week":3,"type":"REG","date":"2025-09-21","home":"TB","away":"NYJ","home_score":29,"away_score":27,"winner":"TB"},{"season":2025,"week":3,"type":"REG","date":"2025-09-21","home":"TEN","away":"IND","home_score":20,"away_score":41,"winner":"IND"},{"season":2025,"week":3,"type":"REG","date":"2025-09-21","home":"WAS","away":"LV","home_score":41,"away_score":24,"winner":"WAS"},{"season":2025,"week":3,"type":"REG","date":"2025-09-21","home":"LAC","away":"DEN","home_score":23,"away_score":20,"winner":"LAC"},{"season":2025,"week":3,"type":"REG","date":"2025-09-21","home":"SEA","away":"NO","home_score":44,"away_score":13,"winner":"SEA"},{"season":2025,"week":3,"type":"REG","date":"2025-09-21","home":"CHI","away":"DAL","home_score":31,"away_score":14,"winner":"CHI"},{"season":2025,"week":3,"type":"REG","date":"2025-09-21","home":"SF","away":"ARI","home_score":16,"away_score":15,"winner":"SF"},{"season":2025,"week":3,"type":"REG","date":"2025-09-21","home":"NYG","away":"KC","home_score":9,"away_score":22,"winner":"KC"},{"season":2025,"week":3,"type":"REG","date":"2025-09-22","home":"BAL","away":"DET","home_score":30,"away_score":38,"winner":"DET"},{"season":2025,"week":4,"type":"REG","date":"2025-09-25","home":"ARI","away":"SEA","home_score":20,"away_score":23,"winner":"SEA"},{"season":2025,"week":4,"type":"REG","date":"2025-09-28","home":"PIT","away":"MIN","home_score":24,"away_score":21,"winner":"PIT"},{"season":2025,"week":4,"type":"REG","date":"2025-09-28","home":"ATL","away":"WAS","home_score":34,"away_score":27,"winner":"ATL"},{"season":2025,"week":4,"type":"REG","date":"2025-09-28","home":"BUF","away":"NO","home_score":31,"away_score":19,"winner":"BUF"},{"season":2025,"week":4,"type":"REG","date":"2025-09-28","home":"DET","away":"CLE","home_score":34,"away_score":10,"winner":"DET"},{"season":2025,"week":4,"type":"REG","date":"2025-09-28","home":"HOU","away":"TEN","home_score":26,"away_score":0,"winner":"HOU"},{"season":2025,"week":4,"type":"REG","date":"2025-09-28","home":"NE","away":"CAR","home_score":42,"away_score":13,"winner":"NE"},{"season":2025,"week":4,"type":"REG","date":"2025-09-28","home":"NYG","away":"LAC","home_score":21,"away_score":18,"winner":"NYG"},{"season":2025,"week":4,"type":"REG","date":"2025-09-28","home":"TB","away":"PHI","home_score":25,"away_score":31,"winner":"PHI"},{"season":2025,"week":4,"type":"REG","date":"2025-09-28","home":"LA","away":"IND","home_score":27,"away_score":20,"winner":"LA"},{"season":2025,"week":4,"type":"REG","date":"2025-09-28","home":"SF","away":"JAX","home_score":21,"away_score":26,"winner":"JAX"},{"season":2025,"week":4,"type":"REG","date":"2025-09-28","home":"KC","away":"BAL","home_score":37,"away_score":20,"winner":"KC"},{"season":2025,"week":4,"type":"REG","date":"2025-09-28","home":"LV","away":"CHI","home_score":24,"away_score":25,"winner":"CHI"},{"season":2025,"week":4,"type":"REG","date":"2025-09-28","home":"DAL","away":"GB","home_score":40,"away_score":40,"winner":"TIE"},{"season":2025,"week":4,"type":"REG","date":"2025-09-29","home":"MIA","away":"NYJ","home_score":27,"away_score":21,"winner":"MIA"},{"season":2025,"week":4,"type":"REG","date":"2025-09-29","home":"DEN","away":"CIN","home_score":28,"away_score":3,"winner":"DEN"},{"season":2025,"week":5,"type":"REG","date":"2025-10-02","home":"LA","away":"SF","home_score":23,"away_score":26,"winner":"SF"},{"season":2025,"week":5,"type":"REG","date":"2025-10-05","home":"CLE","away":"MIN","home_score":17,"away_score":21,"winner":"MIN"},{"season":2025,"week":5,"type":"REG","date":"2025-10-05","home":"BAL","away":"HOU","home_score":10,"away_score":44,"winner":"HOU"},{"season":2025,"week":5,"type":"REG","date":"2025-10-05","home":"CAR","away":"MIA","home_score":27,"away_score":24,"winner":"CAR"},{"season":2025,"week":5,"type":"REG","date":"2025-10-05","home":"IND","away":"LV","home_score":40,"away_score":6,"winner":"IND"},{"season":2025,"week":5,"type":"REG","date":"2025-10-05","home":"NO","away":"NYG","home_score":26,"away_score":14,"winner":"NO"},{"season":2025,"week":5,"type":"REG","date":"2025-10-05","home":"NYJ","away":"DAL","home_score":22,"away_score":37,"winner":"DAL"},{"season":2025,"week":5,"type":"REG","date":"2025-10-05","home":"PHI","away":"DEN","home_score":17,"away_score":21,"winner":"DEN"},{"season":2025,"week":5,"type":"REG","date":"2025-10-05","home":"ARI","away":"TEN","home_score":21,"away_score":22,"winner":"TEN"},{"season":2025,"week":5,"type":"REG","date":"2025-10-05","home":"SEA","away":"TB","home_score":35,"away_score":38,"winner":"TB"},{"season":2025,"week":5,"type":"REG","date":"2025-10-05","home":"CIN","away":"DET","home_score":24,"away_score":37,"winner":"DET"},{"season":2025,"week":5,"type":"REG","date":"2025-10-05","home":"LAC","away":"WAS","home_score":10,"away_score":27,"winner":"WAS"},{"season":2025,"week":5,"type":"REG","date":"2025-10-05","home":"BUF","away":"NE","home_score":20,"away_score":23,"winner":"NE"},{"season":2025,"week":5,"type":"REG","date":"2025-10-06","home":"JAX","away":"KC","home_score":31,"away_score":28,"winner":"JAX"},{"season":2025,"week":6,"type":"REG","date":"2025-10-09","home":"NYG","away":"PHI","home_score":34,"away_score":17,"winner":"NYG"},{"season":2025,"week":6,"type":"REG","date":"2025-10-12","home":"NYJ","away":"DEN","home_score":11,"away_score":13,"winner":"DEN"},{"season":2025,"week":6,"type":"REG","date":"2025-10-12","home":"BAL","away":"LA","home_score":3,"away_score":17,"winner":"LA"},{"season":2025,"week":6,"type":"REG","date":"2025-10-12","home":"CAR","away":"DAL","home_score":30,"away_score":27,"winner":"CAR"},{"season":2025,"week":6,"type":"REG","date":"2025-10-12","home":"IND","away":"ARI","home_score":31,"away_score":27,"winner":"IND"},{"season":2025,"week":6,"type":"REG","date":"2025-10-12","home":"JAX","away":"SEA","home_score":12,"away_score":20,"winner":"SEA"},{"season":2025,"week":6,"type":"REG","date":"2025-10-12","home":"MIA","away":"LAC","home_score":27,"away_score":29,"winner":"LAC"},{"season":2025,"week":6,"type":"REG","date":"2025-10-12","home":"NO","away":"NE","home_score":19,"away_score":25,"winner":"NE"},{"season":2025,"week":6,"type":"REG","date":"2025-10-12","home":"PIT","away":"CLE","home_score":23,"away_score":9,"winner":"PIT"},{"season":2025,"week":6,"type":"REG","date":"2025-10-12","home":"LV","away":"TEN","home_score":20,"away_score":10,"winner":"LV"},{"season":2025,"week":6,"type":"REG","date":"2025-10-12","home":"GB","away":"CIN","home_score":27,"away_score":18,"winner":"GB"},{"season":2025,"week":6,"type":"REG","date":"2025-10-12","home":"TB","away":"SF","home_score":30,"away_score":19,"winner":"TB"},{"season":2025,"week":6,"type":"REG","date":"2025-10-12","home":"KC","away":"DET","home_score":30,"away_score":17,"winner":"KC"},{"season":2025,"week":6,"type":"REG","date":"2025-10-13","home":"ATL","away":"BUF","home_score":24,"away_score":14,"winner":"ATL"},{"season":2025,"week":6,"type":"REG","date":"2025-10-13","home":"WAS","away":"CHI","home_score":24,"away_score":25,"winner":"CHI"},{"season":2025,"week":7,"type":"REG","date":"2025-10-16","home":"CIN","away":"PIT","home_score":33,"away_score":31,"winner":"CIN"},{"season":2025,"week":7,"type":"REG","date":"2025-10-19","home":"JAX","away":"LA","home_score":7,"away_score":35,"winner":"LA"},{"season":2025,"week":7,"type":"REG","date":"2025-10-19","home":"CHI","away":"NO","home_score":26,"away_score":14,"winner":"CHI"},{"season":2025,"week":7,"type":"REG","date":"2025-10-19","home":"CLE","away":"MIA","home_score":31,"away_score":6,"winner":"CLE"},{"season":2025,"week":7,"type":"REG","date":"2025-10-19","home":"KC","away":"LV","home_score":31,"away_score":0,"winner":"KC"},{"season":2025,"week":7,"type":"REG","date":"2025-10-19","home":"MIN","away":"PHI","home_score":22,"away_score":28,"winner":"PHI"},{"season":2025,"week":7,"type":"REG","date":"2025-10-19","home":"NYJ","away":"CAR","home_score":6,"away_score":13,"winner":"CAR"},{"season":2025,"week":7,"type":"REG","date":"2025-10-19","home":"TEN","away":"NE","home_score":13,"away_score":31,"winner":"NE"},{"season":2025,"week":7,"type":"REG","date":"2025-10-19","home":"DEN","away":"NYG","home_score":33,"away_score":32,"winner":"DEN"},{"season":2025,"week":7,"type":"REG","date":"2025-10-19","home":"LAC","away":"IND","home_score":24,"away_score":38,"winner":"IND"},{"season":2025,"week":7,"type":"REG","date":"2025-10-19","home":"ARI","away":"GB","home_score":23,"away_score":27,"winner":"GB"},{"season":2025,"week":7,"type":"REG","date":"2025-10-19","home":"DAL","away":"WAS","home_score":44,"away_score":22,"winner":"DAL"},{"season":2025,"week":7,"type":"REG","date":"2025-10-19","home":"SF","away":"ATL","home_score":20,"away_score":10,"winner":"SF"},{"season":2025,"week":7,"type":"REG","date":"2025-10-20","home":"DET","away":"TB","home_score":24,"away_score":9,"winner":"DET"},{"season":2025,"week":7,"type":"REG","date":"2025-10-20","home":"SEA","away":"HOU","home_score":27,"away_score":19,"winner":"SEA"},{"season":2025,"week":8,"type":"REG","date":"2025-10-23","home":"LAC","away":"MIN","home_score":37,"away_score":10,"winner":"LAC"},{"season":2025,"week":8,"type":"REG","date":"2025-10-26","home":"ATL","away":"MIA","home_score":10,"away_score":34,"winner":"MIA"},{"season":2025,"week":8,"type":"REG","date":"2025-10-26","home":"BAL","away":"CHI","home_score":30,"away_score":16,"winner":"BAL"},{"season":2025,"week":8,"type":"REG","date":"2025-10-26","home":"CAR","away":"BUF","home_score":9,"away_score":40,"winner":"BUF"},{"season":2025,"week":8,"type":"REG","date":"2025-10-26","home":"CIN","away":"NYJ","home_score":38,"away_score":39,"winner":"NYJ"},{"season":2025,"week":8,"type":"REG","date":"2025-10-26","home":"HOU","away":"SF","home_score":26,"away_score":15,"winner":"HOU"},{"season":2025,"week":8,"type":"REG","date":"2025-10-26","home":"NE","away":"CLE","home_score":32,"away_score":13,"winner":"NE"},{"season":2025,"week":8,"type":"REG","date":"2025-10-26","home":"PHI","away":"NYG","home_score":38,"away_score":20,"winner":"PHI"},{"season":2025,"week":8,"type":"REG","date":"2025-10-26","home":"NO","away":"TB","home_score":3,"away_score":23,"winner":"TB"},{"season":2025,"week":8,"type":"REG","date":"2025-10-26","home":"DEN","away":"DAL","home_score":44,"away_score":24,"winner":"DEN"},{"season":2025,"week":8,"type":"REG","date":"2025-10-26","home":"IND","away":"TEN","home_score":38,"away_score":14,"winner":"IND"},{"season":2025,"week":8,"type":"REG","date":"2025-10-26","home":"PIT","away":"GB","home_score":25,"away_score":35,"winner":"GB"},{"season":2025,"week":8,"type":"REG","date":"2025-10-27","home":"KC","away":"WAS","home_score":28,"away_score":7,"winner":"KC"},{"season":2025,"week":9,"type":"REG","date":"2025-10-30","home":"MIA","away":"BAL","home_score":6,"away_score":28,"winner":"BAL"},{"season":2025,"week":9,"type":"REG","date":"2025-11-02","home":"CIN","away":"CHI","home_score":42,"away_score":47,"winner":"CHI"},{"season":2025,"week":9,"type":"REG","date":"2025-11-02","home":"DET","away":"MIN","home_score":24,"away_score":27,"winner":"MIN"},{"season":2025,"week":9,"type":"REG","date":"2025-11-02","home":"GB","away":"CAR","home_score":13,"away_score":16,"winner":"CAR"},{"season":2025,"week":9,"type":"REG","date":"2025-11-02","home":"HOU","away":"DEN","home_score":15,"away_score":18,"winner":"DEN"},{"season":2025,"week":9,"type":"REG","date":"2025-11-02","home":"NE","away":"ATL","home_score":24,"away_score":23,"winner":"NE"},{"season":2025,"week":9,"type":"REG","date":"2025-11-02","home":"NYG","away":"SF","home_score":24,"away_score":34,"winner":"SF"},{"season":2025,"week":9,"type":"REG","date":"2025-11-02","home":"PIT","away":"IND","home_score":27,"away_score":20,"winner":"PIT"},{"season":2025,"week":9,"type":"REG","date":"2025-11-02","home":"TEN","away":"LAC","home_score":20,"away_score":27,"winner":"LAC"},{"season":2025,"week":9,"type":"REG","date":"2025-11-02","home":"LA","away":"NO","home_score":34,"away_score":10,"winner":"LA"},{"season":2025,"week":9,"type":"REG","date":"2025-11-02","home":"LV","away":"JAX","home_score":29,"away_score":30,"winner":"JAX"},{"season":2025,"week":9,"type":"REG","date":"2025-11-02","home":"BUF","away":"KC","home_score":28,"away_score":21,"winner":"BUF"},{"season":2025,"week":9,"type":"REG","date":"2025-11-02","home":"WAS","away":"SEA","home_score":14,"away_score":38,"winner":"SEA"},{"season":2025,"week":9,"type":"REG","date":"2025-11-03","home":"DAL","away":"ARI","home_score":17,"away_score":27,"winner":"ARI"},{"season":2025,"week":10,"type":"REG","date":"2025-11-06","home":"DEN","away":"LV","home_score":10,"away_score":7,"winner":"DEN"},{"season":2025,"week":10,"type":"REG","date":"2025-11-09","home":"IND","away":"ATL","home_score":31,"away_score":25,"winner":"IND"},{"season":2025,"week":10,"type":"REG","date":"2025-11-09","home":"CAR","away":"NO","home_score":7,"away_score":17,"winner":"NO"},{"season":2025,"week":10,"type":"REG","date":"2025-11-09","home":"CHI","away":"NYG","home_score":24,"away_score":20,"winner":"CHI"},{"season":2025,"week":10,"type":"REG","date":"2025-11-09","home":"HOU","away":"JAX","home_score":36,"away_score":29,"winner":"HOU"},{"season":2025,"week":10,"type":"REG","date":"2025-11-09","home":"MIA","away":"BUF","home_score":30,"away_score":13,"winner":"MIA"},{"season":2025,"week":10,"type":"REG","date":"2025-11-09","home":"MIN","away":"BAL","home_score":19,"away_score":27,"winner":"BAL"},{"season":2025,"week":10,"type":"REG","date":"2025-11-09","home":"NYJ","away":"CLE","home_score":27,"away_score":20,"winner":"NYJ"},{"season":2025,"week":10,"type":"REG","date":"2025-11-09","home":"TB","away":"NE","home_score":23,"away_score":28,"winner":"NE"},{"season":2025,"week":10,"type":"REG","date":"2025-11-09","home":"SEA","away":"ARI","home_score":44,"away_score":22,"winner":"SEA"},{"season":2025,"week":10,"type":"REG","date":"2025-11-09","home":"SF","away":"LA","home_score":26,"away_score":42,"winner":"LA"},{"season":2025,"week":10,"type":"REG","date":"2025-11-09","home":"WAS","away":"DET","home_score":22,"away_score":44,"winner":"DET"},{"season":2025,"week":10,"type":"REG","date":"2025-11-09","home":"LAC","away":"PIT","home_score":25,"away_score":10,"winner":"LAC"},{"season":2025,"week":10,"type":"REG","date":"2025-11-10","home":"GB","away":"PHI","home_score":7,"away_score":10,"winner":"PHI"},{"season":2025,"week":11,"type":"REG","date":"2025-11-13","home":"NE","away":"NYJ","home_score":27,"away_score":14,"winner":"NE"},{"season":2025,"week":11,"type":"REG","date":"2025-11-16","home":"MIA","away":"WAS","home_score":16,"away_score":13,"winner":"MIA"},{"season":2025,"week":11,"type":"REG","date":"2025-11-16","home":"ATL","away":"CAR","home_score":27,"away_score":30,"winner":"CAR"},{"season":2025,"week":11,"type":"REG","date":"2025-11-16","home":"BUF","away":"TB","home_score":44,"away_score":32,"winner":"BUF"},{"season":2025,"week":11,"type":"REG","date":"2025-11-16","home":"JAX","away":"LAC","home_score":35,"away_score":6,"winner":"JAX"},{"season":2025,"week":11,"type":"REG","date":"2025-11-16","home":"MIN","away":"CHI","home_score":17,"away_score":19,"winner":"CHI"},{"season":2025,"week":11,"type":"REG","date":"2025-11-16","home":"NYG","away":"GB","home_score":20,"away_score":27,"winner":"GB"},{"season":2025,"week":11,"type":"REG","date":"2025-11-16","home":"PIT","away":"CIN","home_score":34,"away_score":12,"winner":"PIT"},{"season":2025,"week":11,"type":"REG","date":"2025-11-16","home":"TEN","away":"HOU","home_score":13,"away_score":16,"winner":"HOU"},{"season":2025,"week":11,"type":"REG","date":"2025-11-16","home":"ARI","away":"SF","home_score":22,"away_score":41,"winner":"SF"},{"season":2025,"week":11,"type":"REG","date":"2025-11-16","home":"LA","away":"SEA","home_score":21,"away_score":19,"winner":"LA"},{"season":2025,"week":11,"type":"REG","date":"2025-11-16","home":"CLE","away":"BAL","home_score":16,"away_score":23,"winner":"BAL"},{"season":2025,"week":11,"type":"REG","date":"2025-11-16","home":"DEN","away":"KC","home_score":22,"away_score":19,"winner":"DEN"},{"season":2025,"week":11,"type":"REG","date":"2025-11-16","home":"PHI","away":"DET","home_score":16,"away_score":9,"winner":"PHI"},{"season":2025,"week":11,"type":"REG","date":"2025-11-17","home":"LV","away":"DAL","home_score":16,"away_score":33,"winner":"DAL"},{"season":2025,"week":12,"type":"REG","date":"2025-11-20","home":"HOU","away":"BUF","home_score":23,"away_score":19,"winner":"HOU"},{"season":2025,"week":12,"type":"REG","date":"2025-11-23","home":"BAL","away":"NYJ","home_score":23,"away_score":10,"winner":"BAL"},{"season":2025,"week":12,"type":"REG","date":"2025-11-23","home":"CHI","away":"PIT","home_score":31,"away_score":28,"winner":"CHI"},{"season":2025,"week":12,"type":"REG","date":"2025-11-23","home":"CIN","away":"NE","home_score":20,"away_score":26,"winner":"NE"},{"season":2025,"week":12,"type":"REG","date":"2025-11-23","home":"DET","away":"NYG","home_score":34,"away_score":27,"winner":"DET"},{"season":2025,"week":12,"type":"REG","date":"2025-11-23","home":"GB","away":"MIN","home_score":23,"away_score":6,"winner":"GB"},{"season":2025,"week":12,"type":"REG","date":"2025-11-23","home":"KC","away":"IND","home_score":23,"away_score":20,"winner":"KC"},{"season":2025,"week":12,"type":"REG","date":"2025-11-23","home":"TEN","away":"SEA","home_score":24,"away_score":30,"winner":"SEA"},{"season":2025,"week":12,"type":"REG","date":"2025-11-23","home":"ARI","away":"JAX","home_score":24,"away_score":27,"winner":"JAX"},{"season":2025,"week":12,"type":"REG","date":"2025-11-23","home":"LV","away":"CLE","home_score":10,"away_score":24,"winner":"CLE"},{"season":2025,"week":12,"type":"REG","date":"2025-11-23","home":"DAL","away":"PHI","home_score":24,"away_score":21,"winner":"DAL"},{"season":2025,"week":12,"type":"REG","date":"2025-11-23","home":"NO","away":"ATL","home_score":10,"away_score":24,"winner":"ATL"},{"season":2025,"week":12,"type":"REG","date":"2025-11-23","home":"LA","away":"TB","home_score":34,"away_score":7,"winner":"LA"},{"season":2025,"week":12,"type":"REG","date":"2025-11-24","home":"SF","away":"CAR","home_score":20,"away_score":9,"winner":"SF"},{"season":2025,"week":13,"type":"REG","date":"2025-11-27","home":"DET","away":"GB","home_score":24,"away_score":31,"winner":"GB"},{"season":2025,"week":13,"type":"REG","date":"2025-11-27","home":"DAL","away":"KC","home_score":31,"away_score":28,"winner":"DAL"},{"season":2025,"week":13,"type":"REG","date":"2025-11-27","home":"BAL","away":"CIN","home_score":14,"away_score":32,"winner":"CIN"},{"season":2025,"week":13,"type":"REG","date":"2025-11-28","home":"PHI","away":"CHI","home_score":15,"away_score":24,"winner":"CHI"},{"season":2025,"week":13,"type":"REG","date":"2025-11-30","home":"CAR","away":"LA","home_score":31,"away_score":28,"winner":"CAR"},{"season":2025,"week":13,"type":"REG","date":"2025-11-30","home":"CLE","away":"SF","home_score":8,"away_score":26,"winner":"SF"},{"season":2025,"week":13,"type":"REG","date":"2025-11-30","home":"IND","away":"HOU","home_score":16,"away_score":20,"winner":"HOU"},{"season":2025,"week":13,"type":"REG","date":"2025-11-30","home":"MIA","away":"NO","home_score":21,"away_score":17,"winner":"MIA"},{"season":2025,"week":13,"type":"REG","date":"2025-11-30","home":"NYJ","away":"ATL","home_score":27,"away_score":24,"winner":"NYJ"},{"season":2025,"week":13,"type":"REG","date":"2025-11-30","home":"TB","away":"ARI","home_score":20,"away_score":17,"winner":"TB"},{"season":2025,"week":13,"type":"REG","date":"2025-11-30","home":"TEN","away":"JAX","home_score":3,"away_score":25,"winner":"JAX"},{"season":2025,"week":13,"type":"REG","date":"2025-11-30","home":"SEA","away":"MIN","home_score":26,"away_score":0,"winner":"SEA"},{"season":2025,"week":13,"type":"REG","date":"2025-11-30","home":"LAC","away":"LV","home_score":31,"away_score":14,"winner":"LAC"},{"season":2025,"week":13,"type":"REG","date":"2025-11-30","home":"PIT","away":"BUF","home_score":7,"away_score":26,"winner":"BUF"},{"season":2025,"week":13,"type":"REG","date":"2025-11-30","home":"WAS","away":"DEN","home_score":26,"away_score":27,"winner":"DEN"},{"season":2025,"week":13,"type":"REG","date":"2025-12-01","home":"NE","away":"NYG","home_score":33,"away_score":15,"winner":"NE"},{"season":2025,"week":14,"type":"REG","date":"2025-12-04","home":"DET","away":"DAL","home_score":44,"away_score":30,"winner":"DET"},{"season":2025,"week":14,"type":"REG","date":"2025-12-07","home":"ATL","away":"SEA","home_score":9,"away_score":37,"winner":"SEA"},{"season":2025,"week":14,"type":"REG","date":"2025-12-07","home":"BAL","away":"PIT","home_score":22,"away_score":27,"winner":"PIT"},{"season":2025,"week":14,"type":"REG","date":"2025-12-07","home":"CLE","away":"TEN","home_score":29,"away_score":31,"winner":"TEN"},{"season":2025,"week":14,"type":"REG","date":"2025-12-07","home":"GB","away":"CHI","home_score":28,"away_score":21,"winner":"GB"},{"season":2025,"week":14,"type":"REG","date":"2025-12-07","home":"JAX","away":"IND","home_score":36,"away_score":19,"winner":"JAX"},{"season":2025,"week":14,"type":"REG","date":"2025-12-07","home":"MIN","away":"WAS","home_score":31,"away_score":0,"winner":"MIN"},{"season":2025,"week":14,"type":"REG","date":"2025-12-07","home":"NYJ","away":"MIA","home_score":10,"away_score":34,"winner":"MIA"},{"season":2025,"week":14,"type":"REG","date":"2025-12-07","home":"TB","away":"NO","home_score":20,"away_score":24,"winner":"NO"},{"season":2025,"week":14,"type":"REG","date":"2025-12-07","home":"LV","away":"DEN","home_score":17,"away_score":24,"winner":"DEN"},{"season":2025,"week":14,"type":"REG","date":"2025-12-07","home":"ARI","away":"LA","home_score":17,"away_score":45,"winner":"LA"},{"season":2025,"week":14,"type":"REG","date":"2025-12-07","home":"BUF","away":"CIN","home_score":39,"away_score":34,"winner":"BUF"},{"season":2025,"week":14,"type":"REG","date":"2025-12-07","home":"KC","away":"HOU","home_score":10,"away_score":20,"winner":"HOU"},{"season":2025,"week":14,"type":"REG","date":"2025-12-08","home":"LAC","away":"PHI","home_score":22,"away_score":19,"winner":"LAC"},{"season":2025,"week":15,"type":"REG","date":"2025-12-11","home":"TB","away":"ATL","home_score":28,"away_score":29,"winner":"ATL"},{"season":2025,"week":15,"type":"REG","date":"2025-12-14","home":"CHI","away":"CLE","home_score":31,"away_score":3,"winner":"CHI"},{"season":2025,"week":15,"type":"REG","date":"2025-12-14","home":"CIN","away":"BAL","home_score":0,"away_score":24,"winner":"BAL"},{"season":2025,"week":15,"type":"REG","date":"2025-12-14","home":"HOU","away":"ARI","home_score":40,"away_score":20,"winner":"HOU"},{"season":2025,"week":15,"type":"REG","date":"2025-12-14","home":"JAX","away":"NYJ","home_score":48,"away_score":20,"winner":"JAX"},{"season":2025,"week":15,"type":"REG","date":"2025-12-14","home":"KC","away":"LAC","home_score":13,"away_score":16,"winner":"LAC"},{"season":2025,"week":15,"type":"REG","date":"2025-12-14","home":"NE","away":"BUF","home_score":31,"away_score":35,"winner":"BUF"},{"season":2025,"week":15,"type":"REG","date":"2025-12-14","home":"NYG","away":"WAS","home_score":21,"away_score":29,"winner":"WAS"},{"season":2025,"week":15,"type":"REG","date":"2025-12-14","home":"PHI","away":"LV","home_score":31,"away_score":0,"winner":"PHI"},{"season":2025,"week":15,"type":"REG","date":"2025-12-14","home":"DEN","away":"GB","home_score":34,"away_score":26,"winner":"DEN"},{"season":2025,"week":15,"type":"REG","date":"2025-12-14","home":"LA","away":"DET","home_score":41,"away_score":34,"winner":"LA"},{"season":2025,"week":15,"type":"REG","date":"2025-12-14","home":"NO","away":"CAR","home_score":20,"away_score":17,"winner":"NO"},{"season":2025,"week":15,"type":"REG","date":"2025-12-14","home":"SEA","away":"IND","home_score":18,"away_score":16,"winner":"SEA"},{"season":2025,"week":15,"type":"REG","date":"2025-12-14","home":"SF","away":"TEN","home_score":37,"away_score":24,"winner":"SF"},{"season":2025,"week":15,"type":"REG","date":"2025-12-14","home":"DAL","away":"MIN","home_score":26,"away_score":34,"winner":"MIN"},{"season":2025,"week":15,"type":"REG","date":"2025-12-15","home":"PIT","away":"MIA","home_score":28,"away_score":15,"winner":"PIT"},{"season":2025,"week":16,"type":"REG","date":"2025-12-18","home":"SEA","away":"LA","home_score":38,"away_score":37,"winner":"SEA"},{"season":2025,"week":16,"type":"REG","date":"2025-12-20","home":"CHI","away":"GB","home_score":22,"away_score":16,"winner":"CHI"},{"season":2025,"week":16,"type":"REG","date":"2025-12-20","home":"WAS","away":"PHI","home_score":18,"away_score":29,"winner":"PHI"},{"season":2025,"week":16,"type":"REG","date":"2025-12-21","home":"BAL","away":"NE","home_score":24,"away_score":28,"winner":"NE"},{"season":2025,"week":16,"type":"REG","date":"2025-12-21","home":"CAR","away":"TB","home_score":23,"away_score":20,"winner":"CAR"},{"season":2025,"week":16,"type":"REG","date":"2025-12-21","home":"CLE","away":"BUF","home_score":20,"away_score":23,"winner":"BUF"},{"season":2025,"week":16,"type":"REG","date":"2025-12-21","home":"DAL","away":"LAC","home_score":17,"away_score":34,"winner":"LAC"},{"season":2025,"week":16,"type":"REG","date":"2025-12-21","home":"NO","away":"NYJ","home_score":29,"away_score":6,"winner":"NO"},{"season":2025,"week":16,"type":"REG","date":"2025-12-21","home":"NYG","away":"MIN","home_score":13,"away_score":16,"winner":"MIN"},{"season":2025,"week":16,"type":"REG","date":"2025-12-21","home":"TEN","away":"KC","home_score":26,"away_score":9,"winner":"TEN"},{"season":2025,"week":16,"type":"REG","date":"2025-12-21","home":"ARI","away":"ATL","home_score":19,"away_score":26,"winner":"ATL"},{"season":2025,"week":16,"type":"REG","date":"2025-12-21","home":"DEN","away":"JAX","home_score":20,"away_score":34,"winner":"JAX"},{"season":2025,"week":16,"type":"REG","date":"2025-12-21","home":"DET","away":"PIT","home_score":24,"away_score":29,"winner":"PIT"},{"season":2025,"week":16,"type":"REG","date":"2025-12-21","home":"HOU","away":"LV","home_score":23,"away_score":21,"winner":"HOU"},{"season":2025,"week":16,"type":"REG","date":"2025-12-21","home":"MIA","away":"CIN","home_score":21,"away_score":45,"winner":"CIN"},{"season":2025,"week":16,"type":"REG","date":"2025-12-22","home":"IND","away":"SF","home_score":27,"away_score":48,"winner":"SF"},{"season":2025,"week":17,"type":"REG","date":"2025-12-25","home":"WAS","away":"DAL","home_score":23,"away_score":30,"winner":"DAL"},{"season":2025,"week":17,"type":"REG","date":"2025-12-25","home":"MIN","away":"DET","home_score":23,"away_score":10,"winner":"MIN"},{"season":2025,"week":17,"type":"REG","date":"2025-12-25","home":"KC","away":"DEN","home_score":13,"away_score":20,"winner":"DEN"},{"season":2025,"week":17,"type":"REG","date":"2025-12-28","home":"CAR","away":"SEA","home_score":10,"away_score":27,"winner":"SEA"},{"season":2025,"week":17,"type":"REG","date":"2025-12-28","home":"CIN","away":"ARI","home_score":37,"away_score":14,"winner":"CIN"},{"season":2025,"week":17,"type":"REG","date":"2025-12-28","home":"CLE","away":"PIT","home_score":13,"away_score":6,"winner":"CLE"},{"season":2025,"week":17,"type":"REG","date":"2025-12-27","home":"GB","away":"BAL","home_score":24,"away_score":41,"winner":"BAL"},{"season":2025,"week":17,"type":"REG","date":"2025-12-28","home":"IND","away":"JAX","home_score":17,"away_score":23,"winner":"JAX"},{"season":2025,"week":17,"type":"REG","date":"2025-12-27","home":"LAC","away":"HOU","home_score":16,"away_score":20,"winner":"HOU"},{"season":2025,"week":17,"type":"REG","date":"2025-12-28","home":"LV","away":"NYG","home_score":10,"away_score":34,"winner":"NYG"},{"season":2025,"week":17,"type":"REG","date":"2025-12-28","home":"MIA","away":"TB","home_score":20,"away_score":17,"winner":"MIA"},{"season":2025,"week":17,"type":"REG","date":"2025-12-28","home":"NYJ","away":"NE","home_score":10,"away_score":42,"winner":"NE"},{"season":2025,"week":17,"type":"REG","date":"2025-12-28","home":"TEN","away":"NO","home_score":26,"away_score":34,"winner":"NO"},{"season":2025,"week":17,"type":"REG","date":"2025-12-28","home":"BUF","away":"PHI","home_score":12,"away_score":13,"winner":"PHI"},{"season":2025,"week":17,"type":"REG","date":"2025-12-28","home":"SF","away":"CHI","home_score":42,"away_score":38,"winner":"SF"},{"season":2025,"week":17,"type":"REG","date":"2025-12-29","home":"ATL","away":"LA","home_score":27,"away_score":24,"winner":"ATL"},{"season":2025,"week":18,"type":"REG","date":"2026-01-04","home":"ATL","away":"NO","home_score":19,"away_score":17,"winner":"ATL"},{"season":2025,"week":18,"type":"REG","date":"2026-01-04","home":"BUF","away":"NYJ","home_score":35,"away_score":8,"winner":"BUF"},{"season":2025,"week":18,"type":"REG","date":"2026-01-04","home":"CHI","away":"DET","home_score":16,"away_score":19,"winner":"DET"},{"season":2025,"week":18,"type":"REG","date":"2026-01-04","home":"CIN","away":"CLE","home_score":18,"away_score":20,"winner":"CLE"},{"season":2025,"week":18,"type":"REG","date":"2026-01-04","home":"DEN","away":"LAC","home_score":19,"away_score":3,"winner":"DEN"},{"season":2025,"week":18,"type":"REG","date":"2026-01-04","home":"HOU","away":"IND","home_score":38,"away_score":30,"winner":"HOU"},{"season":2025,"week":18,"type":"REG","date":"2026-01-04","home":"JAX","away":"TEN","home_score":41,"away_score":7,"winner":"JAX"},{"season":2025,"week":18,"type":"REG","date":"2026-01-04","home":"LA","away":"ARI","home_score":37,"away_score":20,"winner":"LA"},{"season":2025,"week":18,"type":"REG","date":"2026-01-04","home":"LV","away":"KC","home_score":14,"away_score":12,"winner":"LV"},{"season":2025,"week":18,"type":"REG","date":"2026-01-04","home":"MIN","away":"GB","home_score":16,"away_score":3,"winner":"MIN"},{"season":2025,"week":18,"type":"REG","date":"2026-01-04","home":"NE","away":"MIA","home_score":38,"away_score":10,"winner":"NE"},{"season":2025,"week":18,"type":"REG","date":"2026-01-04","home":"NYG","away":"DAL","home_score":34,"away_score":17,"winner":"NYG"},{"season":2025,"week":18,"type":"REG","date":"2026-01-04","home":"PHI","away":"WAS","home_score":17,"away_score":24,"winner":"WAS"},{"season":2025,"week":18,"type":"REG","date":"2026-01-04","home":"PIT","away":"BAL","home_score":26,"away_score":24,"winner":"PIT"},{"season":2025,"week":18,"type":"REG","date":"2026-01-03","home":"SF","away":"SEA","home_score":3,"away_score":13,"winner":"SEA"},{"season":2025,"week":18,"type":"REG","date":"2026-01-03","home":"TB","away":"CAR","home_score":16,"away_score":14,"winner":"TB"},{"season":2025,"week":19,"type":"WC","date":"2026-01-10","home":"CHI","away":"GB","home_score":31,"away_score":27,"winner":"CHI"},{"season":2025,"week":19,"type":"WC","date":"2026-01-11","home":"JAX","away":"BUF","home_score":24,"away_score":27,"winner":"BUF"},{"season":2025,"week":19,"type":"WC","date":"2026-01-11","home":"PHI","away":"SF","home_score":19,"away_score":23,"winner":"SF"},{"season":2025,"week":19,"type":"WC","date":"2026-01-11","home":"NE","away":"LAC","home_score":16,"away_score":3,"winner":"NE"},{"season":2025,"week":19,"type":"WC","date":"2026-01-12","home":"PIT","away":"HOU","home_score":6,"away_score":30,"winner":"HOU"},{"season":2025,"week":19,"type":"WC","date":"2026-01-10","home":"CAR","away":"LA","home_score":31,"away_score":34,"winner":"LA"},{"season":2025,"week":20,"type":"DIV","date":"2026-01-17","home":"DEN","away":"BUF","home_score":33,"away_score":30,"winner":"DEN"},{"season":2025,"week":20,"type":"DIV","date":"2026-01-17","home":"SEA","away":"SF","home_score":41,"away_score":6,"winner":"SEA"},{"season":2025,"week":20,"type":"DIV","date":"2026-01-18","home":"CHI","away":"LA","home_score":17,"away_score":20,"winner":"LA"},{"season":2025,"week":20,"type":"DIV","date":"2026-01-18","home":"NE","away":"HOU","home_score":28,"away_score":16,"winner":"NE"},{"season":2025,"week":21,"type":"CON","date":"2026-01-25","home":"DEN","away":"NE","home_score":7,"away_score":10,"winner":"NE"},{"season":2025,"week":21,"type":"CON","date":"2026-01-25","home":"SEA","away":"LA","home_score":31,"away_score":27,"winner":"SEA"},{"season":2025,"week":22,"type":"SB","date":"2026-02-08","home":"NE","away":"SEA","home_score":13,"away_score":29,"winner":"SEA"}]